WarrenCowleyParameters/__init__.py
warrencowleyparameters-3.0.1.dist-info/METADATA
warrencowleyparameters-3.0.1.dist-info/WHEEL
warrencowleyparameters-3.0.1.dist-info/entry_points.txt
warrencowleyparameters-3.0.1.dist-info/top_level.txt
warrencowleyparameters-3.0.1.dist-info/RECORD
