Metadata-Version: 2.4
Name: WarrenCowleyParameters
Version: 3.0.1
Summary: OVITO Python modifier to compute Warren-Cowley parameters.
Author-email: Killian Sheriff <ksheriff@mit.edu>
Maintainer-email: Killian Sheriff <ksheriff@mit.edu>
License: MIT License
Project-URL: repository, https://github.com/killiansheriff/WarrenCowleyParameters
Keywords: ovito,python-modifier
Requires-Python: >=3.7
Requires-Dist: ovito>=3.9.1
